rock_paper_scissors_bot/__init__.py
rock_paper_scissors_bot/db.py
rock_paper_scissors_bot/handlers.py
rock_paper_scissors_bot-0.1.0.dist-info/entry_points.txt
rock_paper_scissors_bot-0.1.0.dist-info/LICENSE
rock_paper_scissors_bot-0.1.0.dist-info/WHEEL
rock_paper_scissors_bot-0.1.0.dist-info/METADATA
rock_paper_scissors_bot-0.1.0.dist-info/RECORD
