Metadata-Version: 2.1
Name: rock-paper-scissors-bot
Version: 0.1.0
Summary: 
Author: Maxim Semenov
Author-email: 0rang3max@gmail.com
Requires-Python: >=3.6,<4.0
Classifier: Programming Language :: Python :: 3
Classifier: Programming Language :: Python :: 3.6
Classifier: Programming Language :: Python :: 3.7
Classifier: Programming Language :: Python :: 3.8
Classifier: Programming Language :: Python :: 3.9
Requires-Dist: python-telegram-bot (>=13.2,<14.0)
